eqsormo/__init__.py
eqsormo/ascs.py
eqsormo/sorting_model.py
eqsormo/common/__init__.py
eqsormo/common/base_sorting_model.py
eqsormo/common/compute_ascs.py
eqsormo/common/lazy_npz.py
eqsormo/common/mnl_full_asc.py
eqsormo/common/util.py
eqsormo/tra/__init__.py
eqsormo/tra/clear_market.py
eqsormo/tra/price_income.py
eqsormo/tra/save_load.py
eqsormo/tra/tra_sorting_model.py
eqsormo-0.8.5.dist-info/LICENSE
eqsormo-0.8.5.dist-info/METADATA
eqsormo-0.8.5.dist-info/WHEEL
eqsormo-0.8.5.dist-info/top_level.txt
eqsormo-0.8.5.dist-info/RECORD
