Metadata-Version: 2.1
Name: eqsormo
Version: 0.8.5
Summary: Equilibrium sorting models in Python
Home-page: https://github.com/mattwigway/eqsormo
Author: Matthew Wigginton Conway
Author-email: matt@indicatrix.org
License: UNKNOWN
Platform: UNKNOWN
Classifier: Programming Language :: Python :: 3
Classifier: Operating System :: OS Independent
Classifier: License :: OSI Approved :: Apache Software License
Classifier: Development Status :: 3 - Alpha
Requires-Dist: statsmodels
Requires-Dist: tqdm
Requires-Dist: numpy
Requires-Dist: pandas
Requires-Dist: dill
Requires-Dist: scipy
